[{"id":1907254,"start":"2015-12-08 09:30","finish":"2015-12-08 10:25","session":"Dance Aerobics","location":"Dance Studio","instructor":"Alida","activity":"Dance Aerobics","places_left":0,"buttons":{"book":"#"}},{"id":1907356,"start":"2015-12-08 10:30","finish":"2015-12-08 11:25","session":"Ab Blast","location":"Dance Studio","instructor":"Alida","activity":"Ab Blast","places_left":0,"buttons":{"book":"#"}},{"id":1907458,"start":"2015-12-09 10:00","finish":"2015-12-09 10:55","session":"Cardio Blast","location":"Dance Studio","instructor":"Richard","activity":"Cardio Blast","places_left":0,"buttons":{"book":"#"}},{"id":1907560,"start":"2015-12-09 19:00","finish":"2015-12-09 19:55","session":"Fitness Balls","location":"Dance Studio","instructor":"Alida ","activity":"Fitness Balls","places_left":0,"buttons":{"book":"#"}},{"id":1992159,"start":"2015-12-11 10:00","finish":"2015-12-11 11:00","session":"Bums, Tums \u0026 Thighs","location":"Dance Studio","instructor":"Natasha","activity":"Bums, Tums \u0026 Thighs","places_left":0,"buttons":{"book":"#"}},{"id":1992674,"start":"2015-12-12 11:00","finish":"2015-12-12 12:00","session":"Bootcamp","location":"Dance Studio","instructor":"Michal","activity":"Bootcamp","places_left":0,"buttons":{"book":"#"}},{"id":2143005,"start":"2015-12-07 18:00","finish":"2015-12-07 19:00","session":"Power Pump","location":"Dance Studio","instructor":"Alida","activity":"Power Pump","places_left":0,"buttons":{"book":"#"}},{"id":2143266,"start":"2015-12-07 20:00","finish":"2015-12-07 21:00","session":"Yoga","location":"Dance Studio","instructor":"Linda","activity":"Yoga","places_left":0,"buttons":{"book":"#"}},{"id":2143528,"start":"2015-12-08 18:00","finish":"2015-12-08 19:00","session":"Step \u0026 Sculpt","location":"Dance Studio","instructor":"Alida","activity":"Step \u0026 Sculpt","places_left":0,"buttons":{"book":"#"}},{"id":2144050,"start":"2015-12-10 18:00","finish":"2015-12-10 19:00","session":"Step","location":"Dance Studio","instructor":"Alida","activity":"Step","places_left":0,"buttons":{"book":"#"}},{"id":2144311,"start":"2015-12-10 19:00","finish":"2015-12-10 20:00","session":"Bums, Tums \u0026 Thighs","location":"Dance Studio","instructor":"Alida","activity":"Bums, Tums \u0026 Thighs","places_left":0,"buttons":{"book":"#"}},{"id":2144572,"start":"2015-12-13 10:30","finish":"2015-12-13 11:30","session":"Body Conditioning","location":"Dance Studio","instructor":"Helen","activity":"Body Conditioning","places_left":0,"buttons":{"book":"#"}},{"id":2689220,"start":"2015-12-07 10:00","finish":"2015-12-07 11:00","session":"Body Conditioning","location":"Dance Studio","instructor":"Georgina","activity":"Body Conditioning","places_left":0,"buttons":{"book":"#"}},{"id":2689481,"start":"2015-12-09 11:00","finish":"2015-12-09 12:00","session":"Yoga","location":"Dance Studio","instructor":"Marcus","activity":"Yoga","places_left":0,"buttons":{"book":"#"}},{"id":2751907,"start":"2015-12-11 14:00","finish":"2015-12-11 14:55","session":"Yoga","location":"Dance Studio","instructor":"Marcus","activity":"Yoga","places_left":0,"buttons":{"book":"#"}},{"id":2752168,"start":"2015-12-11 13:00","finish":"2015-12-11 13:55","session":"Yoga","location":"Dance Studio","instructor":"Marcus","activity":"Yoga","places_left":0,"buttons":{"book":"#"}},{"id":4058289,"start":"2015-12-13 12:30","finish":"2015-12-13 13:00","session":"Circuit Training","location":"Sports Hall","instructor":"Junayed","activity":"Circuit Training","places_left":0,"buttons":{"book":"#"}},{"id":4179467,"start":"2015-12-07 12:00","finish":"2015-12-07 12:45","session":"Group Cycle","location":"Group Cycle Studio","instructor":"Charles","activity":"Group Cycle","places_left":0,"buttons":{"book":"#"}},{"id":4179571,"start":"2015-12-08 19:00","finish":"2015-12-08 19:45","session":"Group Cycle","location":"Group Cycle Studio","instructor":"Alida","activity":"Group Cycle","places_left":0,"buttons":{"book":"#"}},{"id":4179675,"start":"2015-12-09 18:00","finish":"2015-12-09 18:45","session":"Group Cycle","location":"Group Cycle Studio","instructor":"Alida","activity":"Group Cycle","places_left":0,"buttons":{"book":"#"}},{"id":4179779,"start":"2015-12-09 09:15","finish":"2015-12-09 10:00","session":"Group Cycle","location":"Group Cycle Studio","instructor":"Richard","activity":"Group Cycle","places_left":0,"buttons":{"book":"#"}},{"id":4179883,"start":"2015-12-13 11:30","finish":"2015-12-13 12:15","session":"Group Cycle","location":"Group Cycle Studio","instructor":"Charles","activity":"Group Cycle","places_left":0,"buttons":{"book":"#"}},{"id":4180085,"start":"2015-12-08 14:30","finish":"2015-12-08 15:00","session":"Functional Circuits","location":"X-Cube ","instructor":"Charles or Junayed","activity":"Functional Circuits","places_left":0,"buttons":{"book":"#"}},{"id":4180189,"start":"2015-12-09 12:00","finish":"2015-12-09 12:30","session":"X-Cube","location":"X-Cube ","instructor":"Charles or Junayed","activity":"X-Cube","places_left":0,"buttons":{"book":"#"}},{"id":4180293,"start":"2015-12-11 17:30","finish":"2015-12-11 18:00","session":"X-Cube","location":"X-Cube ","instructor":"Charles or Junayed","activity":"X-Cube","places_left":0,"buttons":{"book":"#"}},{"id":4314828,"start":"2015-12-12 10:00","finish":"2015-12-12 11:00","session":"Cardio Circuits","location":"Dance Studio","instructor":"Charles","activity":"Cardio Circuits","places_left":0,"buttons":{"book":"#"}},{"id":4327478,"start":"2015-12-10 10:30","finish":"2015-12-10 11:30","session":"Brazilian Dance","location":"Dance Studio","instructor":"Anna","activity":"Brazilian Dance","places_left":0,"buttons":{"book":"#"}},{"id":4428858,"start":"2015-12-09 15:45","finish":"2015-12-09 16:45","session":"Football","location":"Sports Hall","instructor":"Abdul","activity":"Football","places_left":0,"buttons":{"book":"#"}},{"id":4428964,"start":"2015-12-09 16:45","finish":"2015-12-09 17:45","session":"Football","location":"Sports Hall","instructor":"Abdul","activity":"Football","places_left":0,"buttons":{"book":"#"}},{"id":4429068,"start":"2015-12-10 18:00","finish":"2015-12-10 19:00","session":"Judo","location":"Sports Hall","instructor":"Leon","activity":"Judo","places_left":0,"buttons":{"book":"#"}},{"id":4429173,"start":"2015-12-10 19:00","finish":"2015-12-10 20:00","session":"Judo","location":"Sports Hall","instructor":"Leon","activity":"Judo","places_left":0,"buttons":{"book":"#"}},{"id":4429279,"start":"2015-12-10 16:00","finish":"2015-12-10 17:00","session":"Mixed Tennis","location":"Outdoor Tennis Courts","instructor":"Alex","activity":"Mixed Tennis","places_left":0,"buttons":{"book":"#"}},{"id":4429384,"start":"2015-12-10 17:00","finish":"2015-12-10 18:00","session":"Mixed Tennis","location":"Outdoor Tennis Courts","instructor":"Alex","activity":"Mixed Tennis","places_left":0,"buttons":{"book":"#"}},{"id":4429489,"start":"2015-12-10 18:00","finish":"2015-12-10 19:00","session":"Mixed Tennis","location":"Tennis Courts","instructor":"Alex","activity":"Mixed Tennis","places_left":0,"buttons":{"book":"#"}},{"id":4429595,"start":"2015-12-09 17:00","finish":"2015-12-09 19:00","session":"Badminton","location":"Sports Hall","instructor":"Norbert","activity":"Badminton","places_left":0,"buttons":{"book":"#"}},{"id":4619184,"start":"2015-12-10 20:00","finish":"2015-12-10 21:00","session":"Pilates","location":"Dance Studio","instructor":"Liz","activity":"Pilates","places_left":0,"buttons":{"book":"#"}},{"id":4619392,"start":"2015-12-07 15:30","finish":"2015-12-07 16:00","session":"Junior Fitness","location":"Dance Studio","instructor":"Charles","activity":"Junior Fitness","places_left":0,"buttons":{"book":"#"}},{"id":4962902,"start":"2015-12-07 09:00","finish":"2015-12-07 21:00","session":"Tennis for £1","location":"Tennis Courts","instructor":null,"activity":"Tennis for £1","places_left":0,"buttons":{"book":"#"}},{"id":4962903,"start":"2015-12-08 09:00","finish":"2015-12-08 21:00","session":"Tennis for £1","location":"Tennis Courts","instructor":null,"activity":"Tennis for £1","places_left":0,"buttons":{"book":"#"}},{"id":4962904,"start":"2015-12-09 09:00","finish":"2015-12-09 21:00","session":"Tennis for £1","location":"Tennis Courts","instructor":null,"activity":"Tennis for £1","places_left":0,"buttons":{"book":"#"}},{"id":4962905,"start":"2015-12-10 09:00","finish":"2015-12-10 21:00","session":"Tennis for £1","location":"Tennis Courts","instructor":null,"activity":"Tennis for £1","places_left":0,"buttons":{"book":"#"}},{"id":4962906,"start":"2015-12-11 09:00","finish":"2015-12-11 21:00","session":"Tennis for £1","location":"Tennis Courts","instructor":null,"activity":"Tennis for £1","places_left":0,"buttons":{"book":"#"}},{"id":4962907,"start":"2015-12-12 09:00","finish":"2015-12-12 21:00","session":"Tennis for £1","location":"Tennis Courts","instructor":null,"activity":"Tennis for £1","places_left":0,"buttons":{"book":"#"}},{"id":4962908,"start":"2015-12-13 09:00","finish":"2015-12-13 21:00","session":"Tennis for £1","location":"Tennis Courts","instructor":null,"activity":"Tennis for £1","places_left":0,"buttons":{"book":"#"}},{"id":5508779,"start":"2015-12-10 17:15","finish":"2015-12-10 18:00","session":"Group Cycle","location":"Group Cycle Studio","instructor":"Charles","activity":"Group Cycle","places_left":0,"buttons":{"book":"#"}},{"id":6070883,"start":"2015-12-08 16:00","finish":"2015-12-08 16:30","session":"Ballet","location":"Dance Studio","instructor":"Joe ","activity":"Ballet","places_left":0,"buttons":{"book":"#"}},{"id":6071197,"start":"2015-12-08 16:30","finish":"2015-12-08 17:00","session":"Ballet","location":"Dance Studio","instructor":"Joe","activity":"Ballet","places_left":0,"buttons":{"book":"#"}}]