[{"id":2952873,"start":"2015-12-30 07:00","finish":"2015-12-30 18:00","session":"Public Gym Session","location":"Gym","instructor":"","activity":"Public Gym Session","places_left":0,"buttons":{"book":"#"}},{"id":2952874,"start":"2015-12-31 07:00","finish":"2015-12-31 15:00","session":"Public Gym Session","location":"Gym","instructor":"","activity":"Public Gym Session","places_left":0,"buttons":{"book":"#"}},{"id":2952876,"start":"2016-01-04 07:00","finish":"2016-01-04 11:00","session":"Public Gym Session","location":"Gym","instructor":"","activity":"Public Gym Session","places_left":0,"buttons":{"book":"#"}},{"id":2952877,"start":"2016-01-05 07:00","finish":"2016-01-05 11:00","session":"Public Gym Session","location":"Gym","instructor":"","activity":"Public Gym Session","places_left":0,"buttons":{"book":"#"}},{"id":3844894,"start":"2016-01-05 09:15","finish":"2016-01-05 10:10","session":"Body Conditioning","location":"studio","instructor":"Anna","activity":"Body Conditioning","places_left":0,"description":"\u003cp\u003eIt’s a whole body workout that can improve your overall fitness, which also makes it one of our most versatile classes. Body Conditioning classes at Better can help you on your way to get in great shape and feel great about your body.  Focusing on strength, muscular endurance and fitness conditioning, these classes will help to develop a strong and toned physique.\u003cbr /\u003eBody conditioning classes involve a high energy, high impact workout, which typically involves a combination of aerobics and toning. This mixed all-around workout is for all parts of your body giving you a high-intensity workout that hits the parts that other classes miss.  It can be great fun but it's always a lot of hard work so commitment levels must be high as must your motivation.\u003c/p\u003e\r\n\u003cp\u003e\u003cstrong\u003eWhat this class is great for:\u003c/strong\u003e\u003cbr /\u003eThe high-energy head-to-toe workout is a high mixed impact session combining a mixture of aerobics with toning and cardio all rolled into one class. A Body Conditioning class can deliver all-round benefits to every part of your body. This all-inclusive class can help you become more toned and physically fitter.\u003cbr /\u003eSo sign up to a body conditioning class today at your local Better Leisure Centre where you can kick-start your fitness journey. \u003c/p\u003e\r\n\u003cp\u003e\u003cstrong\u003eWho can take part:\u003c/strong\u003e\u003cbr /\u003eDespite being quite an intense workout that requires a reasonable amount of motivation, our instructors will be able to adapt the class to suit different fitness levels.\u003c/p\u003e\r\n\u003cp\u003e\u003cstrong\u003eDifficulty Level:\u003c/strong\u003e\u003cbr /\u003eBeginner - Advanced \u003cbr /\u003e\u003cbr /\u003e\u003cstrong\u003eOther facilities:\u003c/strong\u003e\u003cbr /\u003eChanging and shower facilities are available for use before and after the class.\u003cbr /\u003eYou are recommended to use lockers that are available for any belongings.  Lockers generally take 20p or a \u0026pound;1.00 coin although we do not take any responsibilities for the valuables left in them.\u003c/p\u003e\r\n\u003cp\u003e\u003cstrong\u003eOther classes you might be interested in:\u003c/strong\u003e\u003cbr /\u003eBTT\u003cbr /\u003ePower Pump\u003cbr /\u003e20/20/20\u003c/p\u003e\r\n\u003cp\u003e \u003c/p\u003e","buttons":{"book":"#"}},{"id":4100538,"start":"2016-01-04 18:30","finish":"2016-01-04 19:25","session":"Bums, Tums \u0026 Thighs","location":"studio","instructor":"Ayesha","activity":"Bums, Tums \u0026 Thighs","places_left":0,"description":"\u003cp\u003eBums, Tums \u0026amp; Thighs is a class that does exactly what it says on the tin, a popular workout for women as it works your thighs, glutes and abs. This workout is the most-effective session for better-looking legs, firmer bum and a tighter tum. The Bums, Tums \u0026amp; Thighs class is a workout which consists of a series of exercises that specifically targets these areas. By targeting these areas one after the other you’re tackling all three key problem areas in one fun-packed but very effective class. \u003c/p\u003e\r\n\u003cp\u003e\u003cstrong\u003eWhat this class is great for:\u003c/strong\u003e\u003cbr /\u003eThis class is the ultimate toning session for your lower body. Helping you to tone up \u0026amp; firm up your stomach, hips, thighs and bottom with a high-intensity workout. Come try out this brilliant workout for yourself and sign up to a class at one of the local Better Leisure Centres where you could see a significant improvement in your fitness levels. With a variety of different classes running throughout the week you can find a class that works around your schedule. \u003c/p\u003e\r\n\u003cp\u003e\u003cstrong\u003eWho can take part:\u003c/strong\u003e\u003cbr /\u003eThis specific no-nonsense workout may seem a bit excessive, but our expert trainers know exactly what they’re doing and can help anyone at different fitness levels. \u003c/p\u003e\r\n\u003cp\u003e\u003cstrong\u003eDifficulty Level:\u003c/strong\u003e\u003cbr /\u003eBeginner - Intermediate \u003c/p\u003e\r\n\u003cp\u003e\u003cstrong\u003eOther facilities:\u003c/strong\u003e\u003cbr /\u003eChanging and shower facilities are available for use before and after the class.\u003cbr /\u003eYou are recommended to use lockers that are available for any belongings.  Lockers generally take 20p or a \u0026pound;1.00 coin although we do not take any responsibility for the valuables left in them.\u003c/p\u003e\r\n\u003cp\u003e\u003cstrong\u003eOther classes you might be interested in:\u003c/strong\u003e\u003cbr /\u003e20/20/20\u003cbr /\u003eBody Conditioning\u003cbr /\u003ePower Pump\u003c/p\u003e","buttons":{"book":"#"}},{"id":4100643,"start":"2016-01-04 19:30","finish":"2016-01-04 20:25","session":"Pilates","location":"studio","instructor":"judy","activity":"Pilates","places_left":0,"description":"\u003cp\u003ePilates is a functional way of raising your activity levels, especially if you’d like to improve your mobility or are recovering from an injury. Pilates can be adapted to raise the fitness levels of someone less active, and it can challenge someone very fit. Making it open to both men and women alike and whatever your fitness level, Pilates can accommodate you.\u003c/p\u003e\r\n\u003cp\u003e\u003cstrong\u003eWhat this class is great for:\u003c/strong\u003e\u003cbr /\u003ePilates strengthens the core and can bring many health benefits such as helping with back pain, improving body alignment, posture, flexibility and much more. It is an exercise system that focuses on stretching and strengthening the whole body improving your body’s balance and muscle strength. With a variety of Pilates classes constantly running at one of the Better Leisure Centres you can easily sign up to a Pilates class and reap the benefits today.\u003c/p\u003e\r\n\u003cp\u003e\u003cstrong\u003eWho can take part:\u003c/strong\u003e\u003cbr /\u003ePilates is suitable for people of all levels of fitness. You’re never too late to start; Pilates can be devised into a programme of exercises tailored to your fitness levels. \u003c/p\u003e\r\n\u003cp\u003e\u003cstrong\u003eDifficulty Level:\u003c/strong\u003e\u003cbr /\u003eBeginner - Advanced \u003cbr /\u003e\u003cbr /\u003e\u003cstrong\u003eOther facilities:\u003c/strong\u003e\u003cbr /\u003eChanging and shower facilities are available for use before and after the class.\u003cbr /\u003eYou are recommended to use lockers that are available for any belongings.  Lockers generally take 20p or a \u0026pound;1.00 coin although we do not take any responsibility for the valuables left in them. \u003c/p\u003e\r\n\u003cp\u003e\u003cstrong\u003eOther classes you might be interested in:\u003c/strong\u003e\u003cbr /\u003eCore Stability\u003cbr /\u003eYoga - Hatha\u003cbr /\u003eAb Blast\u003c/p\u003e\r\n\u003cp\u003e \u003c/p\u003e\r\n\u003cp\u003e \u003c/p\u003e\r\n\u003cp\u003e \u003c/p\u003e","buttons":{"book":"#"}},{"id":4104925,"start":"2016-01-05 19:30","finish":"2016-01-05 20:25","session":"Yoga - Hatha","location":"studio","instructor":"sarika","activity":"Yoga - Hatha","places_left":0,"description":"\u003cp\u003eHatha yoga is the mother of yoga and is the most familiar style of yoga in the Western world; as this is the most conventional form of yoga which can be found in classes up and down the UK. The word Hatha is made up of \"ha\" meaning Sun and ‘tha’ meaning Moon representing the positive and negative energy flows in the body. Hatha yoga regulates and balances these energy flows. Hatha is most often used to describe gentle, basic classes with no flow between poses. A hatha class will likely be a slow-paced stretching class with an emphasis on breathing and perhaps seated meditation.\u003c/p\u003e\r\n\u003cp\u003e\u003cstrong\u003eWhat this class is great for:\u003c/strong\u003e\u003cbr /\u003eThis gentle yoga class is great for your wellbeing, posture, body alignment and joints. Hatha Yoga is also a great class to distress and find a relaxing place of Zen. Find your inner peace at Hatha Yoga class at a Better Leisure Centre near you.\u003c/p\u003e\r\n\u003cp\u003e\u003cstrong\u003eWho can take part:\u003c/strong\u003e\u003cbr /\u003eHatha Yoga is a is a good place to learn all the basics making it perfect for beginners to learn the poses, relaxation techniques, and to become comfortable with yoga. Hatha Yoga is suitable for all ages and fitness levels.\u003c/p\u003e\r\n\u003cp\u003e\u003cstrong\u003eDifficulty Level:\u003c/strong\u003e\u003cbr /\u003eBeginner - Advanced \u003cbr /\u003e\u003cbr /\u003e\u003cstrong\u003eOther facilities:\u003c/strong\u003e\u003cbr /\u003eChanging and shower facilities are available for use before and after the class.\u003cbr /\u003eYou are recommended to use lockers that are available for any belongings.  Lockers generally take 20p or a \u0026pound;1.00 coin although we do not take any responsibility for the valuables left in them.\u003c/p\u003e\r\n\u003cp\u003e\u003cstrong\u003eOther classes you might be interested in:\u003c/strong\u003e\u003cbr /\u003eYoga – Iyengar\u003c/p\u003e","buttons":{"book":"#"}},{"id":4105029,"start":"2015-12-30 09:45","finish":"2015-12-30 10:40","session":"Pilates","location":"studio","instructor":"judy","activity":"Pilates","places_left":0,"description":"\u003cp\u003ePilates is a functional way of raising your activity levels, especially if you’d like to improve your mobility or are recovering from an injury. Pilates can be adapted to raise the fitness levels of someone less active, and it can challenge someone very fit. Making it open to both men and women alike and whatever your fitness level, Pilates can accommodate you.\u003c/p\u003e\r\n\u003cp\u003e\u003cstrong\u003eWhat this class is great for:\u003c/strong\u003e\u003cbr /\u003ePilates strengthens the core and can bring many health benefits such as helping with back pain, improving body alignment, posture, flexibility and much more. It is an exercise system that focuses on stretching and strengthening the whole body improving your body’s balance and muscle strength. With a variety of Pilates classes constantly running at one of the Better Leisure Centres you can easily sign up to a Pilates class and reap the benefits today.\u003c/p\u003e\r\n\u003cp\u003e\u003cstrong\u003eWho can take part:\u003c/strong\u003e\u003cbr /\u003ePilates is suitable for people of all levels of fitness. You’re never too late to start; Pilates can be devised into a programme of exercises tailored to your fitness levels. \u003c/p\u003e\r\n\u003cp\u003e\u003cstrong\u003eDifficulty Level:\u003c/strong\u003e\u003cbr /\u003eBeginner - Advanced \u003cbr /\u003e\u003cbr /\u003e\u003cstrong\u003eOther facilities:\u003c/strong\u003e\u003cbr /\u003eChanging and shower facilities are available for use before and after the class.\u003cbr /\u003eYou are recommended to use lockers that are available for any belongings.  Lockers generally take 20p or a \u0026pound;1.00 coin although we do not take any responsibility for the valuables left in them. \u003c/p\u003e\r\n\u003cp\u003e\u003cstrong\u003eOther classes you might be interested in:\u003c/strong\u003e\u003cbr /\u003eCore Stability\u003cbr /\u003eYoga - Hatha\u003cbr /\u003eAb Blast\u003c/p\u003e\r\n\u003cp\u003e \u003c/p\u003e\r\n\u003cp\u003e \u003c/p\u003e\r\n\u003cp\u003e \u003c/p\u003e","buttons":{"book":"#"}},{"id":5153492,"start":"2016-01-02 08:30","finish":"2016-01-02 16:00","session":"Swim For All","location":"Main Pool","instructor":"","activity":"Swim For All","places_left":0,"description":"\u003cp\u003eThis is a general swim for everyone - all ages and all abilities although swim safely rules do apply.\u003c/p\u003e\r\n\u003cp\u003eJust come along at the times listed and enjoy your swim in our pool.\u003c/p\u003e\r\n\u003cp\u003e \u003c/p\u003e","buttons":{"book":"#"}},{"id":5153596,"start":"2016-01-02 16:00","finish":"2016-01-02 18:00","session":"Swim For Women","location":"Main Pool","instructor":null,"activity":"Swim For Women","places_left":0,"description":"\u003cp\u003eThis is a swimming session for women only, aged 16 and over. \u003c/p\u003e\r\n\u003cp\u003eJust come along at the times listed and enjoy your swim in our pool - note that swim safely rules do apply.\u003c/p\u003e\r\n\u003cp\u003e \u003c/p\u003e","buttons":{"book":"#"}},{"id":5153700,"start":"2016-01-02 09:30","finish":"2016-01-02 16:00","session":"Swim for Families","location":"Teaching Pool","instructor":"","activity":"Swim for Families","places_left":0,"description":"\u003cp\u003eA dedicated swimming session for families to make the most of quality time together in a fun, pool environment.\u003c/p\u003e","buttons":{"book":"#"}},{"id":5153805,"start":"2016-01-03 09:30","finish":"2016-01-03 16:00","session":"Swim For All","location":"Main Pool","instructor":null,"activity":"Swim For All","places_left":0,"description":"\u003cp\u003eThis is a general swim for everyone - all ages and all abilities although swim safely rules do apply.\u003c/p\u003e\r\n\u003cp\u003eJust come along at the times listed and enjoy your swim in our pool.\u003c/p\u003e\r\n\u003cp\u003e \u003c/p\u003e","buttons":{"book":"#"}},{"id":5154120,"start":"2016-01-03 09:30","finish":"2016-01-03 16:00","session":"Swim for Families","location":"Teaching Pool","instructor":"","activity":"Swim for Families","places_left":0,"description":"\u003cp\u003eA dedicated swimming session for families to make the most of quality time together in a fun, pool environment.\u003c/p\u003e","buttons":{"book":"#"}},{"id":5154270,"start":"2016-01-02 13:00","finish":"2016-01-02 15:00","session":"Junior Gym","location":"Gym","instructor":null,"activity":"Junior Gym","places_left":0,"buttons":{"book":"#"}},{"id":5154271,"start":"2016-01-03 13:00","finish":"2016-01-03 15:00","session":"Junior Gym","location":"Gym","instructor":null,"activity":"Junior Gym","places_left":0,"buttons":{"book":"#"}},{"id":5265935,"start":"2016-01-05 18:30","finish":"2016-01-05 19:15","session":"Cardio Circuits","location":"studio","instructor":"Michael","activity":"Cardio Circuits","places_left":0,"buttons":{"book":"#"}},{"id":6170363,"start":"2015-12-31 09:45","finish":"2015-12-31 10:40","session":"Bums, Tums \u0026 Thighs","location":"studio","instructor":"Elisa","activity":"Bums, Tums \u0026 Thighs","places_left":0,"description":"\u003cp\u003eBums, Tums \u0026amp; Thighs is a class that does exactly what it says on the tin, a popular workout for women as it works your thighs, glutes and abs. This workout is the most-effective session for better-looking legs, firmer bum and a tighter tum. The Bums, Tums \u0026amp; Thighs class is a workout which consists of a series of exercises that specifically targets these areas. By targeting these areas one after the other you’re tackling all three key problem areas in one fun-packed but very effective class. \u003c/p\u003e\r\n\u003cp\u003e\u003cstrong\u003eWhat this class is great for:\u003c/strong\u003e\u003cbr /\u003eThis class is the ultimate toning session for your lower body. Helping you to tone up \u0026amp; firm up your stomach, hips, thighs and bottom with a high-intensity workout. Come try out this brilliant workout for yourself and sign up to a class at one of the local Better Leisure Centres where you could see a significant improvement in your fitness levels. With a variety of different classes running throughout the week you can find a class that works around your schedule. \u003c/p\u003e\r\n\u003cp\u003e\u003cstrong\u003eWho can take part:\u003c/strong\u003e\u003cbr /\u003eThis specific no-nonsense workout may seem a bit excessive, but our expert trainers know exactly what they’re doing and can help anyone at different fitness levels. \u003c/p\u003e\r\n\u003cp\u003e\u003cstrong\u003eDifficulty Level:\u003c/strong\u003e\u003cbr /\u003eBeginner - Intermediate \u003c/p\u003e\r\n\u003cp\u003e\u003cstrong\u003eOther facilities:\u003c/strong\u003e\u003cbr /\u003eChanging and shower facilities are available for use before and after the class.\u003cbr /\u003eYou are recommended to use lockers that are available for any belongings.  Lockers generally take 20p or a \u0026pound;1.00 coin although we do not take any responsibility for the valuables left in them.\u003c/p\u003e\r\n\u003cp\u003e\u003cstrong\u003eOther classes you might be interested in:\u003c/strong\u003e\u003cbr /\u003e20/20/20\u003cbr /\u003eBody Conditioning\u003cbr /\u003ePower Pump\u003c/p\u003e","buttons":{"book":"#"}},{"id":6633921,"start":"2016-01-04 16:30","finish":"2016-01-04 21:30","session":"Public Gym Session","location":"Gym","instructor":null,"activity":"Public Gym Session","places_left":0,"buttons":{"book":"#"}},{"id":6633922,"start":"2016-01-05 16:30","finish":"2016-01-05 21:30","session":"Public Gym Session","location":"Gym","instructor":null,"activity":"Public Gym Session","places_left":0,"buttons":{"book":"#"}},{"id":6689756,"start":"2016-01-05 10:00","finish":"2016-01-05 10:45","session":"Water Workout","location":"Main Pool","instructor":"Lina","activity":"Water Workout","places_left":0,"description":"\u003cp\u003eTake a dip in the pool and feel refreshed whilst working out with a Water Workout. A typical water class would involve an invigorating workout that you would expect in a dry class, but because it’s in the water it allows you to exercise without excess pressure on the joints and creates more resistance giving you an even greater workout.\u003c/p\u003e\r\n\u003cp\u003e\u003cstrong\u003eWhat this class is great for:\u003c/strong\u003e\u003cbr /\u003eExercising in the water is a great way to condition and relieve stress as you can really create a big splash when working out, injecting a fun element into working out. The best thing about working out in the water is that the temperature of the water helps stop you from getting too warm. There are tons of extra bonuses that you can only get when working out in the water including improvements in mobility, coordination and an improvement in core strength. Find a Water Workout that’s suitable for you at a local Better Leisure Centre where you could really splash away those calories.\u003c/p\u003e\r\n\u003cp\u003e\u003cstrong\u003eWho can take part:\u003c/strong\u003e\u003cbr /\u003eWater Workout is suitable for adults of all ages and open to all ability levels. You don’t even need to know how to swim as this class takes place within the shallow end of the pool. But it’s recommended that you know how to swim to take part.\u003c/p\u003e\r\n\u003cp\u003e\u003cstrong\u003eDifficulty Level:\u003c/strong\u003e\u003cbr /\u003eBeginner - Advanced\u003cbr /\u003e\u003cbr /\u003e\u003cstrong\u003eOther facilities:\u003c/strong\u003e\u003cbr /\u003eChanging and shower facilities are available for use before and after the class.\u003cbr /\u003eYou are recommended to use lockers that are available for any belongings.  Lockers generally take 20p or a \u0026pound;1.00 coin although we do not take any responsibility for the valuables left in them.\u003c/p\u003e\r\n\u003cp\u003e\u003cstrong\u003eOther classes you might be interested in:\u003c/strong\u003e\u003cbr /\u003eAerobics\u003cbr /\u003ePilates\u003c/p\u003e","buttons":{"book":"#"}},{"id":6800916,"start":"2015-12-30 14:15","finish":"2015-12-30 15:30","session":"Splash Time with Inflatables","location":"Main Pool","instructor":null,"activity":"Splash Time with Inflatables","places_left":0,"buttons":{"book":"#"}},{"id":6800920,"start":"2016-01-03 16:00","finish":"2016-01-03 17:00","session":"Splash Time with Inflatables","location":"Main Pool","instructor":"","activity":"Splash Time with Inflatables","places_left":0,"buttons":{"book":"#"}},{"id":6800921,"start":"2016-01-04 14:15","finish":"2016-01-04 15:30","session":"Splash Time with Inflatables","location":"Main Pool","instructor":null,"activity":"Splash Time with Inflatables","places_left":0,"buttons":{"book":"#"}},{"id":6800924,"start":"2015-12-30 07:00","finish":"2015-12-30 09:00","session":"Swim For Adults","location":"Main Pool","instructor":"","activity":"Swim For Adults","places_left":0,"description":"\u003cp\u003eThis is a swimming session adults only, aged 16 and over. \u003c/p\u003e\r\n\u003cp\u003eJust come along at the times listed and enjoy your swim in our pool - note that swim safely rules do apply.\u003c/p\u003e\r\n\u003cp\u003e \u003c/p\u003e","buttons":{"book":"#"}},{"id":6800925,"start":"2015-12-31 07:00","finish":"2015-12-31 09:00","session":"Swim For Adults","location":"Main Pool","instructor":"","activity":"Swim For Adults","places_left":0,"description":"\u003cp\u003eThis is a swimming session adults only, aged 16 and over. \u003c/p\u003e\r\n\u003cp\u003eJust come along at the times listed and enjoy your swim in our pool - note that swim safely rules do apply.\u003c/p\u003e\r\n\u003cp\u003e \u003c/p\u003e","buttons":{"book":"#"}},{"id":6800928,"start":"2015-12-30 09:00","finish":"2015-12-30 17:00","session":"Swim For All","location":"Main Pool","instructor":null,"activity":"Swim For All","places_left":0,"description":"\u003cp\u003eThis is a general swim for everyone - all ages and all abilities although swim safely rules do apply.\u003c/p\u003e\r\n\u003cp\u003eJust come along at the times listed and enjoy your swim in our pool.\u003c/p\u003e\r\n\u003cp\u003e \u003c/p\u003e","buttons":{"book":"#"}},{"id":6800929,"start":"2015-12-31 09:00","finish":"2015-12-31 14:00","session":"Swim For All","location":"Main Pool","instructor":"","activity":"Swim For All","places_left":0,"description":"\u003cp\u003eThis is a general swim for everyone - all ages and all abilities although swim safely rules do apply.\u003c/p\u003e\r\n\u003cp\u003eJust come along at the times listed and enjoy your swim in our pool.\u003c/p\u003e\r\n\u003cp\u003e \u003c/p\u003e","buttons":{"book":"#"}},{"id":6800934,"start":"2016-01-02 08:30","finish":"2016-01-02 16:00","session":"Public Gym Session","location":"Gym","instructor":"","activity":"Public Gym Session","places_left":0,"buttons":{"book":"#"}},{"id":6800935,"start":"2016-01-03 09:30","finish":"2016-01-03 17:00","session":"Public Gym Session","location":"Gym","instructor":"","activity":"Public Gym Session","places_left":0,"buttons":{"book":"#"}},{"id":6801147,"start":"2015-12-30 09:30","finish":"2015-12-30 17:00","session":"Swim for Families","location":"Teaching Pool","instructor":null,"activity":"Swim for Families","places_left":0,"description":"\u003cp\u003eA dedicated swimming session for families to make the most of quality time together in a fun, pool environment.\u003c/p\u003e","buttons":{"book":"#"}},{"id":6801148,"start":"2015-12-31 09:30","finish":"2015-12-31 14:00","session":"Swim for Families","location":"Teaching Pool","instructor":"","activity":"Swim for Families","places_left":0,"description":"\u003cp\u003eA dedicated swimming session for families to make the most of quality time together in a fun, pool environment.\u003c/p\u003e","buttons":{"book":"#"}},{"id":6801151,"start":"2016-01-04 09:30","finish":"2016-01-04 17:00","session":"Swim for Families","location":"Teaching Pool","instructor":null,"activity":"Swim for Families","places_left":0,"description":"\u003cp\u003eA dedicated swimming session for families to make the most of quality time together in a fun, pool environment.\u003c/p\u003e","buttons":{"book":"#"}},{"id":6801367,"start":"2015-12-30 11:00","finish":"2015-12-30 12:30","session":"Junior Gym","location":"Gym","instructor":null,"activity":"Junior Gym","places_left":0,"buttons":{"book":"#"}},{"id":6801368,"start":"2015-12-31 11:00","finish":"2015-12-31 12:30","session":"Junior Gym","location":"Gym","instructor":null,"activity":"Junior Gym","places_left":0,"buttons":{"book":"#"}},{"id":7054140,"start":"2016-01-04 09:45","finish":"2016-01-04 10:40","session":"Body Conditioning","location":"studio","instructor":"Pauline","activity":"Body Conditioning","places_left":0,"description":"\u003cp\u003eIt’s a whole body workout that can improve your overall fitness, which also makes it one of our most versatile classes. Body Conditioning classes at Better can help you on your way to get in great shape and feel great about your body.  Focusing on strength, muscular endurance and fitness conditioning, these classes will help to develop a strong and toned physique.\u003cbr /\u003eBody conditioning classes involve a high energy, high impact workout, which typically involves a combination of aerobics and toning. This mixed all-around workout is for all parts of your body giving you a high-intensity workout that hits the parts that other classes miss.  It can be great fun but it's always a lot of hard work so commitment levels must be high as must your motivation.\u003c/p\u003e\r\n\u003cp\u003e\u003cstrong\u003eWhat this class is great for:\u003c/strong\u003e\u003cbr /\u003eThe high-energy head-to-toe workout is a high mixed impact session combining a mixture of aerobics with toning and cardio all rolled into one class. A Body Conditioning class can deliver all-round benefits to every part of your body. This all-inclusive class can help you become more toned and physically fitter.\u003cbr /\u003eSo sign up to a body conditioning class today at your local Better Leisure Centre where you can kick-start your fitness journey. \u003c/p\u003e\r\n\u003cp\u003e\u003cstrong\u003eWho can take part:\u003c/strong\u003e\u003cbr /\u003eDespite being quite an intense workout that requires a reasonable amount of motivation, our instructors will be able to adapt the class to suit different fitness levels.\u003c/p\u003e\r\n\u003cp\u003e\u003cstrong\u003eDifficulty Level:\u003c/strong\u003e\u003cbr /\u003eBeginner - Advanced \u003cbr /\u003e\u003cbr /\u003e\u003cstrong\u003eOther facilities:\u003c/strong\u003e\u003cbr /\u003eChanging and shower facilities are available for use before and after the class.\u003cbr /\u003eYou are recommended to use lockers that are available for any belongings.  Lockers generally take 20p or a \u0026pound;1.00 coin although we do not take any responsibilities for the valuables left in them.\u003c/p\u003e\r\n\u003cp\u003e\u003cstrong\u003eOther classes you might be interested in:\u003c/strong\u003e\u003cbr /\u003eBTT\u003cbr /\u003ePower Pump\u003cbr /\u003e20/20/20\u003c/p\u003e\r\n\u003cp\u003e \u003c/p\u003e","buttons":{"book":"#"}}]